eagerx_dcsc_setups/__init__.py
eagerx_dcsc_setups/pendulum/__init__.py
eagerx_dcsc_setups/pendulum/nodes.py
eagerx_dcsc_setups/pendulum/objects.py
eagerx_dcsc_setups/pendulum/ode/__init__.py
eagerx_dcsc_setups/pendulum/ode/engine_nodes.py
eagerx_dcsc_setups/pendulum/ode/pendulum_ode.py
eagerx_dcsc_setups/pendulum/ode/pendulum_render.py
eagerx_dcsc_setups/pendulum/overlay.py
eagerx_dcsc_setups/pendulum/pid.py
eagerx_dcsc_setups/pendulum/processors.py
eagerx_dcsc_setups/pendulum/real/__init__.py
eagerx_dcsc_setups/pendulum/real/engine_nodes.py
eagerx_dcsc_setups/pendulum/real/engine_states.py
eagerx_dcsc_setups-0.1.14.dist-info/LICENSE
eagerx_dcsc_setups-0.1.14.dist-info/WHEEL
eagerx_dcsc_setups-0.1.14.dist-info/METADATA
eagerx_dcsc_setups-0.1.14.dist-info/RECORD
